odoo9_addon_openeducat_transportation-9.0.2.4.0-py2.7-nspkg.pth
odoo_addons/openeducat_transportation/__openerp__.py
odoo_addons/openeducat_transportation/transportation_menu.xml
odoo_addons/openeducat_transportation/__init__.py
odoo_addons/openeducat_transportation/security/ir.model.access.csv
odoo_addons/openeducat_transportation/models/transportation.py
odoo_addons/openeducat_transportation/models/vehicle.py
odoo_addons/openeducat_transportation/models/stop.py
odoo_addons/openeducat_transportation/models/__init__.py
odoo_addons/openeducat_transportation/i18n/openeducat_transportation.pot
odoo_addons/openeducat_transportation/views/vehicle_view.xml
odoo_addons/openeducat_transportation/views/transportation_view.xml
odoo_addons/openeducat_transportation/views/stop_view.xml
odoo_addons/openeducat_transportation/demo/op.transportation.csv
odoo_addons/openeducat_transportation/demo/op.vehicle.csv
odoo_addons/openeducat_transportation/demo/op.stop.csv
odoo_addons/openeducat_transportation/static/description/openeducat_logo.png
odoo_addons/openeducat_transportation/static/description/transportation.png
odoo_addons/openeducat_transportation/static/description/index.html
odoo_addons/openeducat_transportation/static/description/stops.png
odoo_addons/openeducat_transportation/static/description/openeducat_transportation_banner.jpg
odoo_addons/openeducat_transportation/static/description/vehicle.png
odoo_addons/openeducat_transportation/static/description/icon.png
odoo9_addon_openeducat_transportation-9.0.2.4.0.dist-info/top_level.txt
odoo9_addon_openeducat_transportation-9.0.2.4.0.dist-info/WHEEL
odoo9_addon_openeducat_transportation-9.0.2.4.0.dist-info/RECORD
odoo9_addon_openeducat_transportation-9.0.2.4.0.dist-info/metadata.json
odoo9_addon_openeducat_transportation-9.0.2.4.0.dist-info/DESCRIPTION.rst
odoo9_addon_openeducat_transportation-9.0.2.4.0.dist-info/METADATA
odoo9_addon_openeducat_transportation-9.0.2.4.0.dist-info/namespace_packages.txt
